llama_index/tools/quercle/__init__.py
llama_index/tools/quercle/base.py
llama_index/tools/quercle/py.typed
llama_index_tools_quercle-0.1.0.dist-info/METADATA
llama_index_tools_quercle-0.1.0.dist-info/WHEEL
llama_index_tools_quercle-0.1.0.dist-info/licenses/LICENSE
llama_index_tools_quercle-0.1.0.dist-info/RECORD
