Metadata-Version: 2.4
Name: llama-index-tools-quercle
Version: 0.1.0
Summary: Quercle tools for LlamaIndex - AI-powered web fetch and search
Project-URL: Homepage, https://github.com/quercledev/quercle-llama-index
Project-URL: Repository, https://github.com/quercledev/quercle-llama-index
Author-email: Quercle <support@quercle.dev>
License-Expression: MIT
License-File: LICENSE
Keywords: ai,llamaindex,llm,quercle,tools,web-search
Classifier: Development Status :: 4 - Beta
Classifier: Programming Language :: Python :: 3.10
Classifier: Programming Language :: Python :: 3.11
Classifier: Programming Language :: Python :: 3.12
Classifier: Programming Language :: Python :: 3.13
Requires-Python: >=3.10
Requires-Dist: llama-index-core>=0.12.0
Requires-Dist: quercle>=0.1.3
Provides-Extra: dev
Requires-Dist: pytest-asyncio>=0.24; extra == 'dev'
Requires-Dist: pytest>=8.0; extra == 'dev'
Requires-Dist: ruff>=0.9; extra == 'dev'
Requires-Dist: ty>=0.0.1a7; extra == 'dev'
